fastapi_skywalking_middleware/__init__.py
fastapi_skywalking_middleware/_version.py
fastapi_skywalking_middleware/middleware/__init__.py
fastapi_skywalking_middleware-0.2.0.dist-info/LICENSE
fastapi_skywalking_middleware-0.2.0.dist-info/METADATA
fastapi_skywalking_middleware-0.2.0.dist-info/WHEEL
fastapi_skywalking_middleware-0.2.0.dist-info/top_level.txt
fastapi_skywalking_middleware-0.2.0.dist-info/RECORD
