Metadata-Version: 2.1
Name: fastapi-skywalking-middleware
Version: 0.2.0
Summary: A FastAPI Middleware of Skywalking(APM) to trace your service method calls.
Home-page: https://github.com/sunhailin-Leo/fastapi_skywalking_middleware
Author: sunhailin-Leo
Author-email: 379978424@qq.com
License: MIT
Keywords: fastapi,apache-skywalking,skywalking,middleware
Platform: UNKNOWN
Classifier: Development Status :: 5 - Production/Stable
Classifier: Environment :: Console
Classifier: Intended Audience :: Developers
Classifier: License :: OSI Approved :: MIT License
Classifier: Operating System :: OS Independent
Classifier: Programming Language :: Python
Classifier: Programming Language :: Python :: 3.7
Classifier: Programming Language :: Python :: 3.8
Classifier: Programming Language :: Python :: 3.9
Classifier: Programming Language :: Python :: 3.10
Classifier: Programming Language :: Python :: 3.11
Classifier: Topic :: Software Development :: Libraries
Requires-Dist: fastapi
Requires-Dist: apache-skywalking
